redfish_client/__init__.py
redfish_client/caching_connector.py
redfish_client/connector.py
redfish_client/exceptions.py
redfish_client/resource.py
redfish_client/root.py
redfish_client-0.3.9.dist-info/LICENSE
redfish_client-0.3.9.dist-info/METADATA
redfish_client-0.3.9.dist-info/WHEEL
redfish_client-0.3.9.dist-info/pbr.json
redfish_client-0.3.9.dist-info/top_level.txt
redfish_client-0.3.9.dist-info/RECORD
